{
    "name": "RPMTW Top Members Report",
    "url": "https://translate.rpmtw.com/project/resourcepack-mod-zhtw",
    "unit": "words",
    "dateRange": {
        "from": "2024-08-12",
        "to": "2024-09-12"
    },
    "language": {
        "id": "zh-TW",
        "name": "Chinese Traditional"
    },
    "data": [
        {
            "user": {
                "id": "16548599",
                "username": "brian.bm.1216",
                "fullName": "bm (brian.bm.1216)",
                "avatarUrl": "https://crowdin-static.downloads.crowdin.com/avatar/16548599/medium/b296bfd7b8d3ac8215a3a78f19ccca3e.png",
                "joined": "2024-08-28 03:47:23"
            },
            "languages": [
                {
                    "id": "zh-TW",
                    "name": "Chinese Traditional"
                }
            ],
            "translated": 383,
            "target": 597,
            "approved": 0,
            "voted": 1,
            "positiveVotes": 0,
            "negativeVotes": 0,
            "winning": 0
        },
        {
            "user": {
                "id": "16536633",
                "username": "YIIIIIIIIIII",
                "fullName": "冰霜 (YIIIIIIIIIII)",
                "avatarUrl": "https://crowdin-static.downloads.crowdin.com/avatar/16536633/medium/61ef3b09a54362a7df7605c5e7ee87a3.jpeg",
                "joined": "2024-08-20 00:48:59"
            },
            "languages": [
                {
                    "id": "zh-TW",
                    "name": "Chinese Traditional"
                }
            ],
            "translated": 25,
            "target": 1,
            "approved": 0,
            "voted": 0,
            "positiveVotes": 0,
            "negativeVotes": 0,
            "winning": 0
        },
        {
            "user": {
                "id": "14036188",
                "username": "chesterccj305",
                "fullName": "舞秋風 (chesterccj305)",
                "avatarUrl": "https://crowdin-static.downloads.crowdin.com/avatar/14036188/medium/d750d1c59d600f884737c94a369d4787.gif",
                "joined": "2021-03-01 15:40:11"
            },
            "languages": [],
            "translated": 0,
            "target": 0,
            "approved": 0,
            "voted": 0,
            "positiveVotes": 1,
            "negativeVotes": 0,
            "winning": 0
        },
        {
            "user": {
                "id": "13686089",
                "username": "zica87",
                "fullName": "zica (zica87)",
                "avatarUrl": "https://crowdin-static.downloads.crowdin.com/avatar/13686089/medium/d4f6929410f3fc7eceb0fa6bf595a51c.jpg",
                "joined": "2021-05-11 08:16:59"
            },
            "languages": [],
            "translated": 0,
            "target": 0,
            "approved": 0,
            "voted": 0,
            "positiveVotes": 1,
            "negativeVotes": 0,
            "winning": 0
        },
        {
            "user": {
                "id": "16535383",
                "username": "a548778763",
                "fullName": "XXK F (a548778763)",
                "avatarUrl": "https://crowdin-static.downloads.crowdin.com/avatar/16535383/medium/550de34ae471005b7935b8b7997fc60f.png",
                "joined": "2024-08-19 07:18:20"
            },
            "languages": [
                {
                    "id": "zh-TW",
                    "name": "Chinese Traditional"
                }
            ],
            "translated": 0,
            "target": 0,
            "approved": 0,
            "voted": 1,
            "positiveVotes": 0,
            "negativeVotes": 0,
            "winning": 0
        }
    ]
}