{
    "progress": "82.391%",
    "1.12": "86.716%",
    "1.16": "82.357%",
    "1.17": "44.585%",
    "1.18": "43.203%",
    "data": {
        "1.17": {
            "translated": 60105,
            "total": 134809
        },
        "1.12": {
            "translated": 1072443,
            "total": 1236728
        },
        "1.18": {
            "translated": 3054,
            "total": 7069
        },
        "1.16": {
            "translated": 968510,
            "total": 1175993
        }
    }
}