{
    "progress": "75.542%",
    "1.12": "78.359%",
    "1.16": "82.777%",
    "1.17": "51.336%",
    "1.18": "31.117%",
    "1.19": "8.862%",
    "data": {
        "1.18": {
            "translated": 52238,
            "total": 167878
        },
        "1.19": {
            "translated": 3106,
            "total": 35050
        },
        "1.17": {
            "translated": 76176,
            "total": 148388
        },
        "1.12": {
            "translated": 1196660,
            "total": 1527147
        },
        "1.16": {
            "translated": 1026632,
            "total": 1240239
        }
    }
}