{
    "progress": "78.626%",
    "1.12": "79.591%",
    "1.16": "83.224%",
    "1.17": "47.438%",
    "1.18": "39.300%",
    "data": {
        "1.17": {
            "translated": 64177,
            "total": 135285
        },
        "1.18": {
            "translated": 27353,
            "total": 69601
        },
        "1.12": {
            "translated": 1177562,
            "total": 1479510
        },
        "1.16": {
            "translated": 986156,
            "total": 1184942
        }
    }
}