{
    "progress": "76.960%",
    "1.12": "78.977%",
    "1.16": "81.431%",
    "1.17": "50.312%",
    "1.18": "44.992%",
    "1.19": "95.836%",
    "data": {
        "1.19": {
            "translated": 46081,
            "total": 48083
        },
        "1.18": {
            "translated": 82270,
            "total": 182856
        },
        "1.17": {
            "translated": 73806,
            "total": 146698
        },
        "1.16": {
            "translated": 1026484,
            "total": 1260557
        },
        "1.12": {
            "translated": 1221824,
            "total": 1547067
        }
    }
}